{
  "capturedAt": "2026-04-30T10:58:21.486Z",
  "inputs": {
    "days": 90,
    "tenorDays": 14
  },
  "sampleCount": 2161,
  "regimeBands": {
    "low": {
      "upTo": 50
    },
    "moderate": {
      "upTo": 65
    },
    "elevated": {
      "upTo": 80
    },
    "high": {
      "upTo": null
    }
  },
  "cells": [
    {
      "regime": "low",
      "slPct": 2,
      "direction": "long",
      "tenorDays": 14,
      "sampleCount": 776,
      "dvolMean": 44.00875000000001,
      "dvolMin": 39.2,
      "dvolMax": 49.92,
      "spotMean": 74603.13351804123,
      "perDayUsdPer1k_mean": 1.7823099536801956,
      "perDayUsdPer1k_p25": 1.6813409703648678,
      "perDayUsdPer1k_p50": 1.7697966008913752,
      "perDayUsdPer1k_p75": 1.9020032855065492,
      "perDayUsdPer1k_p90": 1.993026949539967,
      "upfrontUsdPer1k_mean": 24.95233935152275
    },
    {
      "regime": "low",
      "slPct": 2,
      "direction": "short",
      "tenorDays": 14,
      "sampleCount": 776,
      "dvolMean": 44.00875000000001,
      "dvolMin": 39.2,
      "dvolMax": 49.92,
      "spotMean": 74603.13351804123,
      "perDayUsdPer1k_mean": 1.830089856410953,
      "perDayUsdPer1k_p25": 1.7269745977458766,
      "perDayUsdPer1k_p50": 1.8173196068300523,
      "perDayUsdPer1k_p75": 1.952336592516348,
      "perDayUsdPer1k_p90": 2.0452868379853384,
      "upfrontUsdPer1k_mean": 25.621257989753378
    },
    {
      "regime": "low",
      "slPct": 3,
      "direction": "long",
      "tenorDays": 14,
      "sampleCount": 776,
      "dvolMean": 44.00875000000001,
      "dvolMin": 39.2,
      "dvolMax": 49.92,
      "spotMean": 74603.13351804123,
      "perDayUsdPer1k_mean": 1.496149390840487,
      "perDayUsdPer1k_p25": 1.3990041279209662,
      "perDayUsdPer1k_p50": 1.4838321452316792,
      "perDayUsdPer1k_p75": 1.611031745918328,
      "perDayUsdPer1k_p90": 1.6988621764673864,
      "upfrontUsdPer1k_mean": 20.946091471766835
    },
    {
      "regime": "low",
      "slPct": 3,
      "direction": "short",
      "tenorDays": 14,
      "sampleCount": 776,
      "dvolMean": 44.00875000000001,
      "dvolMin": 39.2,
      "dvolMax": 49.92,
      "spotMean": 74603.13351804123,
      "perDayUsdPer1k_mean": 1.5654388805120025,
      "perDayUsdPer1k_p25": 1.4649850843688303,
      "perDayUsdPer1k_p50": 1.5527319709949736,
      "perDayUsdPer1k_p75": 1.6842637237711204,
      "perDayUsdPer1k_p90": 1.7750581128569176,
      "upfrontUsdPer1k_mean": 21.916144327168023
    },
    {
      "regime": "low",
      "slPct": 5,
      "direction": "long",
      "tenorDays": 14,
      "sampleCount": 776,
      "dvolMean": 44.00875000000001,
      "dvolMin": 39.2,
      "dvolMax": 49.92,
      "spotMean": 74603.13351804123,
      "perDayUsdPer1k_mean": 1.0203170275383626,
      "perDayUsdPer1k_p25": 0.9341688128333543,
      "perDayUsdPer1k_p50": 1.008591927538372,
      "perDayUsdPer1k_p75": 1.121391195873943,
      "perDayUsdPer1k_p90": 1.2000213124885697,
      "upfrontUsdPer1k_mean": 14.28443838553711
    },
    {
      "regime": "low",
      "slPct": 5,
      "direction": "short",
      "tenorDays": 14,
      "sampleCount": 776,
      "dvolMean": 44.00875000000001,
      "dvolMin": 39.2,
      "dvolMax": 49.92,
      "spotMean": 74603.13351804123,
      "perDayUsdPer1k_mean": 1.123972109227191,
      "perDayUsdPer1k_p25": 1.031929736755835,
      "perDayUsdPer1k_p50": 1.111570317064132,
      "perDayUsdPer1k_p75": 1.2320873440723297,
      "perDayUsdPer1k_p90": 1.3159801465973413,
      "upfrontUsdPer1k_mean": 15.735609529180673
    },
    {
      "regime": "low",
      "slPct": 10,
      "direction": "long",
      "tenorDays": 14,
      "sampleCount": 776,
      "dvolMean": 44.00875000000001,
      "dvolMin": 39.2,
      "dvolMax": 49.92,
      "spotMean": 74603.13351804123,
      "perDayUsdPer1k_mean": 0.3153982021809951,
      "perDayUsdPer1k_p25": 0.2668008993412216,
      "perDayUsdPer1k_p50": 0.3065998229675314,
      "perDayUsdPer1k_p75": 0.370226049811803,
      "perDayUsdPer1k_p90": 0.4167178283332283,
      "upfrontUsdPer1k_mean": 4.415574830533924
    },
    {
      "regime": "low",
      "slPct": 10,
      "direction": "short",
      "tenorDays": 14,
      "sampleCount": 776,
      "dvolMean": 44.00875000000001,
      "dvolMin": 39.2,
      "dvolMax": 49.92,
      "spotMean": 74603.13351804123,
      "perDayUsdPer1k_mean": 0.4404568196288999,
      "perDayUsdPer1k_p25": 0.3792810145331233,
      "perDayUsdPer1k_p50": 0.43002357779162353,
      "perDayUsdPer1k_p75": 0.5101206789455466,
      "perDayUsdPer1k_p90": 0.567996010523857,
      "upfrontUsdPer1k_mean": 6.166395474804612
    },
    {
      "regime": "moderate",
      "slPct": 2,
      "direction": "long",
      "tenorDays": 14,
      "sampleCount": 1364,
      "dvolMean": 53.960036656891496,
      "dvolMin": 50.02,
      "dvolMax": 64.4,
      "spotMean": 68898.04909824047,
      "perDayUsdPer1k_mean": 2.318946092550074,
      "perDayUsdPer1k_p25": 2.232264296962691,
      "perDayUsdPer1k_p50": 2.2982874648776184,
      "perDayUsdPer1k_p75": 2.383327236157485,
      "perDayUsdPer1k_p90": 2.4689872206422545,
      "upfrontUsdPer1k_mean": 32.46524529570098
    },
    {
      "regime": "moderate",
      "slPct": 2,
      "direction": "short",
      "tenorDays": 14,
      "sampleCount": 1364,
      "dvolMean": 53.960036656891496,
      "dvolMin": 50.02,
      "dvolMax": 64.4,
      "spotMean": 68898.04909824047,
      "perDayUsdPer1k_mean": 2.3780558822846247,
      "perDayUsdPer1k_p25": 2.2895609154641816,
      "perDayUsdPer1k_p50": 2.3569681775359963,
      "perDayUsdPer1k_p75": 2.443787434355677,
      "perDayUsdPer1k_p90": 2.531236452252497,
      "upfrontUsdPer1k_mean": 33.29278235198464
    },
    {
      "regime": "moderate",
      "slPct": 3,
      "direction": "long",
      "tenorDays": 14,
      "sampleCount": 1364,
      "dvolMean": 53.960036656891496,
      "dvolMin": 50.02,
      "dvolMax": 64.4,
      "spotMean": 68898.04909824047,
      "perDayUsdPer1k_mean": 2.0148371576666726,
      "perDayUsdPer1k_p25": 1.9305336601622767,
      "perDayUsdPer1k_p50": 1.994651014668424,
      "perDayUsdPer1k_p75": 2.0773370259467407,
      "perDayUsdPer1k_p90": 2.160732208117282,
      "upfrontUsdPer1k_mean": 28.207720207333452
    },
    {
      "regime": "moderate",
      "slPct": 3,
      "direction": "short",
      "tenorDays": 14,
      "sampleCount": 1364,
      "dvolMean": 53.960036656891496,
      "dvolMin": 50.02,
      "dvolMax": 64.4,
      "spotMean": 68898.04909824047,
      "perDayUsdPer1k_mean": 2.1015355463453735,
      "perDayUsdPer1k_p25": 2.014458607257508,
      "perDayUsdPer1k_p50": 2.080695444436288,
      "perDayUsdPer1k_p75": 2.1661038939524144,
      "perDayUsdPer1k_p90": 2.2522334571509233,
      "upfrontUsdPer1k_mean": 29.421497648835192
    },
    {
      "regime": "moderate",
      "slPct": 5,
      "direction": "long",
      "tenorDays": 14,
      "sampleCount": 1364,
      "dvolMean": 53.960036656891496,
      "dvolMin": 50.02,
      "dvolMax": 64.4,
      "spotMean": 68898.04909824047,
      "perDayUsdPer1k_mean": 1.4873240097151972,
      "perDayUsdPer1k_p25": 1.4098728273711287,
      "perDayUsdPer1k_p50": 1.4684948052878661,
      "perDayUsdPer1k_p75": 1.5443974455907337,
      "perDayUsdPer1k_p90": 1.6212712924393435,
      "upfrontUsdPer1k_mean": 20.822536136012683
    },
    {
      "regime": "moderate",
      "slPct": 5,
      "direction": "short",
      "tenorDays": 14,
      "sampleCount": 1364,
      "dvolMean": 53.960036656891496,
      "dvolMin": 50.02,
      "dvolMax": 64.4,
      "spotMean": 68898.04909824047,
      "perDayUsdPer1k_mean": 1.6218115528146217,
      "perDayUsdPer1k_p25": 1.5394906210353356,
      "perDayUsdPer1k_p50": 1.601842808051611,
      "perDayUsdPer1k_p75": 1.682527685562013,
      "perDayUsdPer1k_p90": 1.7641948010862711,
      "upfrontUsdPer1k_mean": 22.705361739404758
    },
    {
      "regime": "moderate",
      "slPct": 10,
      "direction": "long",
      "tenorDays": 14,
      "sampleCount": 1364,
      "dvolMean": 53.960036656891496,
      "dvolMin": 50.02,
      "dvolMax": 64.4,
      "spotMean": 68898.04909824047,
      "perDayUsdPer1k_mean": 0.6003799848061973,
      "perDayUsdPer1k_p25": 0.5482847042546005,
      "perDayUsdPer1k_p50": 0.586769662019057,
      "perDayUsdPer1k_p75": 0.637602559011685,
      "perDayUsdPer1k_p90": 0.6901657836105466,
      "upfrontUsdPer1k_mean": 8.405319787286755
    },
    {
      "regime": "moderate",
      "slPct": 10,
      "direction": "short",
      "tenorDays": 14,
      "sampleCount": 1364,
      "dvolMean": 53.960036656891496,
      "dvolMin": 50.02,
      "dvolMax": 64.4,
      "spotMean": 68898.04909824047,
      "perDayUsdPer1k_mean": 0.7923909624254668,
      "perDayUsdPer1k_p25": 0.7295022397269938,
      "perDayUsdPer1k_p50": 0.7762317645240113,
      "perDayUsdPer1k_p75": 0.8376621654361999,
      "perDayUsdPer1k_p90": 0.9008704550340677,
      "upfrontUsdPer1k_mean": 11.093473473956546
    },
    {
      "regime": "elevated",
      "slPct": 2,
      "direction": "long",
      "tenorDays": 14,
      "sampleCount": 16,
      "dvolMean": 71.02187500000001,
      "dvolMin": 65.27,
      "dvolMax": 77.15,
      "spotMean": 65788.16625000001,
      "perDayUsdPer1k_mean": 3.2464716558956224,
      "perDayUsdPer1k_p25": 3.1127887373985703,
      "perDayUsdPer1k_p50": 3.213607644307603,
      "perDayUsdPer1k_p75": 3.3128349748692334,
      "perDayUsdPer1k_p90": 3.4175560985179425,
      "upfrontUsdPer1k_mean": 45.45060318253872
    },
    {
      "regime": "elevated",
      "slPct": 2,
      "direction": "short",
      "tenorDays": 14,
      "sampleCount": 16,
      "dvolMean": 71.02187500000001,
      "dvolMin": 65.27,
      "dvolMax": 77.15,
      "spotMean": 65788.16625000001,
      "perDayUsdPer1k_mean": 3.3248376401486888,
      "perDayUsdPer1k_p25": 3.188398079439948,
      "perDayUsdPer1k_p50": 3.2912984423771374,
      "perDayUsdPer1k_p75": 3.3925721456042566,
      "perDayUsdPer1k_p90": 3.499450728744867,
      "upfrontUsdPer1k_mean": 46.547726962081626
    },
    {
      "regime": "elevated",
      "slPct": 3,
      "direction": "long",
      "tenorDays": 14,
      "sampleCount": 16,
      "dvolMean": 71.02187500000001,
      "dvolMin": 65.27,
      "dvolMax": 77.15,
      "spotMean": 65788.16625000001,
      "perDayUsdPer1k_mean": 2.9214251552634685,
      "perDayUsdPer1k_p25": 2.7901772110072813,
      "perDayUsdPer1k_p50": 2.889081877643034,
      "perDayUsdPer1k_p75": 2.986494616931766,
      "perDayUsdPer1k_p90": 3.089369775148474,
      "upfrontUsdPer1k_mean": 40.89995217368857
    },
    {
      "regime": "elevated",
      "slPct": 3,
      "direction": "short",
      "tenorDays": 14,
      "sampleCount": 16,
      "dvolMean": 71.02187500000001,
      "dvolMin": 65.27,
      "dvolMax": 77.15,
      "spotMean": 65788.16625000001,
      "perDayUsdPer1k_mean": 3.0374627238687344,
      "perDayUsdPer1k_p25": 2.902029933903685,
      "perDayUsdPer1k_p50": 3.0040965338332497,
      "perDayUsdPer1k_p75": 3.1046160567338026,
      "perDayUsdPer1k_p90": 3.21076479489675,
      "upfrontUsdPer1k_mean": 42.52447813416227
    },
    {
      "regime": "elevated",
      "slPct": 5,
      "direction": "long",
      "tenorDays": 14,
      "sampleCount": 16,
      "dvolMean": 71.02187500000001,
      "dvolMin": 65.27,
      "dvolMax": 77.15,
      "spotMean": 65788.16625000001,
      "perDayUsdPer1k_mean": 2.334004011814167,
      "perDayUsdPer1k_p25": 2.2096365126435757,
      "perDayUsdPer1k_p50": 2.303114691386873,
      "perDayUsdPer1k_p75": 2.3953982065062163,
      "perDayUsdPer1k_p90": 2.4930713622807055,
      "upfrontUsdPer1k_mean": 32.67605616539834
    },
    {
      "regime": "elevated",
      "slPct": 5,
      "direction": "short",
      "tenorDays": 14,
      "sampleCount": 16,
      "dvolMean": 71.02187500000001,
      "dvolMin": 65.27,
      "dvolMax": 77.15,
      "spotMean": 65788.16625000001,
      "perDayUsdPer1k_mean": 2.519551896503804,
      "perDayUsdPer1k_p25": 2.3879646722764325,
      "perDayUsdPer1k_p50": 2.486906974131383,
      "perDayUsdPer1k_p75": 2.584551210134049,
      "perDayUsdPer1k_p90": 2.687864700631362,
      "upfrontUsdPer1k_mean": 35.273726551053244
    },
    {
      "regime": "elevated",
      "slPct": 10,
      "direction": "long",
      "tenorDays": 14,
      "sampleCount": 16,
      "dvolMean": 71.02187500000001,
      "dvolMin": 65.27,
      "dvolMax": 77.15,
      "spotMean": 65788.16625000001,
      "perDayUsdPer1k_mean": 1.2191229346005228,
      "perDayUsdPer1k_p25": 1.1215803428254605,
      "perDayUsdPer1k_p50": 1.19395839273807,
      "perDayUsdPer1k_p75": 1.2662467954101253,
      "perDayUsdPer1k_p90": 1.3435996942416657,
      "upfrontUsdPer1k_mean": 17.067721084407317
    },
    {
      "regime": "elevated",
      "slPct": 10,
      "direction": "short",
      "tenorDays": 14,
      "sampleCount": 16,
      "dvolMean": 71.02187500000001,
      "dvolMin": 65.27,
      "dvolMax": 77.15,
      "spotMean": 65788.16625000001,
      "perDayUsdPer1k_mean": 1.5245780640717526,
      "perDayUsdPer1k_p25": 1.4110517871300867,
      "perDayUsdPer1k_p50": 1.495549051449362,
      "perDayUsdPer1k_p75": 1.5797084075377767,
      "perDayUsdPer1k_p90": 1.6695293473778572,
      "upfrontUsdPer1k_mean": 21.34409289700454
    },
    {
      "regime": "high",
      "slPct": 2,
      "direction": "long",
      "tenorDays": 14,
      "sampleCount": 5,
      "dvolMean": 86.194,
      "dvolMin": 82.62,
      "dvolMax": 89.78,
      "spotMean": 63334.674,
      "perDayUsdPer1k_mean": 4.074649144673281,
      "perDayUsdPer1k_p25": 3.9771654266353544,
      "perDayUsdPer1k_p50": 4.085344160468753,
      "perDayUsdPer1k_p75": 4.160752098195309,
      "perDayUsdPer1k_p90": 4.160752098195309,
      "upfrontUsdPer1k_mean": 57.04508802542593
    },
    {
      "regime": "high",
      "slPct": 2,
      "direction": "short",
      "tenorDays": 14,
      "sampleCount": 5,
      "dvolMean": 86.194,
      "dvolMin": 82.62,
      "dvolMax": 89.78,
      "spotMean": 63334.674,
      "perDayUsdPer1k_mean": 4.170037714240874,
      "perDayUsdPer1k_p25": 4.070557005733518,
      "perDayUsdPer1k_p50": 4.180953016558967,
      "perDayUsdPer1k_p75": 4.257905703738811,
      "perDayUsdPer1k_p90": 4.257905703738811,
      "upfrontUsdPer1k_mean": 58.38052799937223
    },
    {
      "regime": "high",
      "slPct": 3,
      "direction": "long",
      "tenorDays": 14,
      "sampleCount": 5,
      "dvolMean": 86.194,
      "dvolMin": 82.62,
      "dvolMax": 89.78,
      "spotMean": 63334.674,
      "perDayUsdPer1k_mean": 3.7362396251611125,
      "perDayUsdPer1k_p25": 3.6401185449890763,
      "perDayUsdPer1k_p50": 3.74674766885802,
      "perDayUsdPer1k_p75": 3.821101872445932,
      "perDayUsdPer1k_p90": 3.821101872445932,
      "upfrontUsdPer1k_mean": 52.307354752255584
    },
    {
      "regime": "high",
      "slPct": 3,
      "direction": "short",
      "tenorDays": 14,
      "sampleCount": 5,
      "dvolMean": 86.194,
      "dvolMin": 82.62,
      "dvolMax": 89.78,
      "spotMean": 63334.674,
      "perDayUsdPer1k_mean": 3.8780725607486146,
      "perDayUsdPer1k_p25": 3.7789310575184425,
      "perDayUsdPer1k_p50": 3.8889148187976064,
      "perDayUsdPer1k_p75": 3.96560542753526,
      "perDayUsdPer1k_p90": 3.96560542753526,
      "upfrontUsdPer1k_mean": 54.29301585048061
    },
    {
      "regime": "high",
      "slPct": 5,
      "direction": "long",
      "tenorDays": 14,
      "sampleCount": 5,
      "dvolMean": 86.194,
      "dvolMin": 82.62,
      "dvolMax": 89.78,
      "spotMean": 63334.674,
      "perDayUsdPer1k_mean": 3.1114858169172583,
      "perDayUsdPer1k_p25": 3.0191094024107206,
      "perDayUsdPer1k_p50": 3.1214665518981057,
      "perDayUsdPer1k_p75": 3.1929251096820046,
      "perDayUsdPer1k_p90": 3.1929251096820046,
      "upfrontUsdPer1k_mean": 43.56080143684161
    },
    {
      "regime": "high",
      "slPct": 5,
      "direction": "short",
      "tenorDays": 14,
      "sampleCount": 5,
      "dvolMean": 86.194,
      "dvolMin": 82.62,
      "dvolMax": 89.78,
      "spotMean": 63334.674,
      "perDayUsdPer1k_mean": 3.34132647166829,
      "perDayUsdPer1k_p25": 3.243790092589702,
      "perDayUsdPer1k_p50": 3.351883016803924,
      "perDayUsdPer1k_p75": 3.4273329485639814,
      "perDayUsdPer1k_p90": 3.4273329485639814,
      "upfrontUsdPer1k_mean": 46.778570603356066
    },
    {
      "regime": "high",
      "slPct": 10,
      "direction": "long",
      "tenorDays": 14,
      "sampleCount": 5,
      "dvolMean": 86.194,
      "dvolMin": 82.62,
      "dvolMax": 89.78,
      "spotMean": 63334.674,
      "perDayUsdPer1k_mean": 1.8505446731866049,
      "perDayUsdPer1k_p25": 1.7728283957464865,
      "perDayUsdPer1k_p50": 1.858449838257514,
      "perDayUsdPer1k_p75": 1.9185722901082556,
      "perDayUsdPer1k_p90": 1.9185722901082556,
      "upfrontUsdPer1k_mean": 25.90762542461247
    },
    {
      "regime": "high",
      "slPct": 10,
      "direction": "short",
      "tenorDays": 14,
      "sampleCount": 5,
      "dvolMean": 86.194,
      "dvolMin": 82.62,
      "dvolMax": 89.78,
      "spotMean": 63334.674,
      "perDayUsdPer1k_mean": 2.253356555587557,
      "perDayUsdPer1k_p25": 2.1644032257826398,
      "perDayUsdPer1k_p50": 2.262538416441623,
      "perDayUsdPer1k_p75": 2.331352817270413,
      "perDayUsdPer1k_p90": 2.331352817270413,
      "upfrontUsdPer1k_mean": 31.546991778225795
    }
  ]
}
